odoo8_addon_account_invoice_supplierinfo_update_on_validate-8.0.1.0.0.99.dev5-py2.7-nspkg.pth
odoo8_addon_account_invoice_supplierinfo_update_on_validate-8.0.1.0.0.99.dev5.dist-info/DESCRIPTION.rst
odoo8_addon_account_invoice_supplierinfo_update_on_validate-8.0.1.0.0.99.dev5.dist-info/METADATA
odoo8_addon_account_invoice_supplierinfo_update_on_validate-8.0.1.0.0.99.dev5.dist-info/RECORD
odoo8_addon_account_invoice_supplierinfo_update_on_validate-8.0.1.0.0.99.dev5.dist-info/WHEEL
odoo8_addon_account_invoice_supplierinfo_update_on_validate-8.0.1.0.0.99.dev5.dist-info/metadata.json
odoo8_addon_account_invoice_supplierinfo_update_on_validate-8.0.1.0.0.99.dev5.dist-info/namespace_packages.txt
odoo8_addon_account_invoice_supplierinfo_update_on_validate-8.0.1.0.0.99.dev5.dist-info/top_level.txt
odoo_addons/account_invoice_supplierinfo_update_on_validate/README.rst
odoo_addons/account_invoice_supplierinfo_update_on_validate/__init__.py
odoo_addons/account_invoice_supplierinfo_update_on_validate/__openerp__.py
odoo_addons/account_invoice_supplierinfo_update_on_validate/demo/account_invoice.xml
odoo_addons/account_invoice_supplierinfo_update_on_validate/i18n/ca.po
odoo_addons/account_invoice_supplierinfo_update_on_validate/i18n/de.po
odoo_addons/account_invoice_supplierinfo_update_on_validate/i18n/es.po
odoo_addons/account_invoice_supplierinfo_update_on_validate/i18n/fi.po
odoo_addons/account_invoice_supplierinfo_update_on_validate/i18n/fr.po
odoo_addons/account_invoice_supplierinfo_update_on_validate/i18n/fr_CH.po
odoo_addons/account_invoice_supplierinfo_update_on_validate/i18n/hr.po
odoo_addons/account_invoice_supplierinfo_update_on_validate/i18n/it.po
odoo_addons/account_invoice_supplierinfo_update_on_validate/i18n/nl.po
odoo_addons/account_invoice_supplierinfo_update_on_validate/i18n/pt_BR.po
odoo_addons/account_invoice_supplierinfo_update_on_validate/i18n/pt_PT.po
odoo_addons/account_invoice_supplierinfo_update_on_validate/i18n/sl.po
odoo_addons/account_invoice_supplierinfo_update_on_validate/i18n/tr.po
odoo_addons/account_invoice_supplierinfo_update_on_validate/static/description/icon.png
odoo_addons/account_invoice_supplierinfo_update_on_validate/tests/__init__.py
odoo_addons/account_invoice_supplierinfo_update_on_validate/tests/test_account_invoice_supplierinfo_update.py
odoo_addons/account_invoice_supplierinfo_update_on_validate/views/account_invoice_view.xml
odoo_addons/account_invoice_supplierinfo_update_on_validate/wizard/__init__.py
odoo_addons/account_invoice_supplierinfo_update_on_validate/wizard/wizard_update_invoice_supplierinfo.py
