Metadata-Version: 2.0
Name: odoo8-addon-account-invoice-supplierinfo-update-on-validate
Version: 8.0.1.0.0.99.dev5
Summary: In the supplier invoice, to validation proposes to update all products whose unit price on the line is different from the supplier price
Home-page: http://akretion.com
Author: Akretion, Odoo Community Association (OCA)
Author-email: support@odoo-community.org
License: AGPL-3
Platform: UNKNOWN
Classifier: Programming Language :: Python :: 2.7
Classifier: Framework :: Odoo
Classifier: License :: OSI Approved :: GNU Affero General Public License v3
Requires-Dist: odoo (<9.0a,>=8.0a)
Requires-Dist: odoo8-addon-account-invoice-supplierinfo-update
